haliax/__about__.py
haliax/__init__.py
haliax/axis.py
haliax/core.py
haliax/debug.py
haliax/hof.py
haliax/jax_utils.py
haliax/ops.py
haliax/partitioning.py
haliax/quantization.py
haliax/random.py
haliax/specialized_fns.py
haliax/tree_util.py
haliax/types.py
haliax/util.py
haliax/wrap.py
haliax/_src/__init__.py
haliax/_src/compile_utils.py
haliax/_src/dot.py
haliax/_src/einsum.py
haliax/_src/fp8.py
haliax/_src/parsing.py
haliax/_src/rearrange.py
haliax/_src/util.py
haliax/nn/__init__.py
haliax/nn/activations.py
haliax/nn/attention.py
haliax/nn/conv.py
haliax/nn/dropout.py
haliax/nn/embedding.py
haliax/nn/linear.py
haliax/nn/loss.py
haliax/nn/mlp.py
haliax/nn/normalization.py
haliax/nn/pool.py
haliax/nn/scan.py
haliax-1.3.dist-info/METADATA
haliax-1.3.dist-info/WHEEL
haliax-1.3.dist-info/licenses/LICENSE
haliax-1.3.dist-info/RECORD
