Metadata-Version: 2.3
Name: haliax
Version: 1.3
Summary: Named Tensors for Legible Deep Learning in JAX
Project-URL: Homepage, https://github.com/stanford-crfm/haliax
Project-URL: Bug Tracker, https://github.com/stanford-crfm/haliax/issues/
Author-email: David Hall <dlwh@cs.stanford.edu>
License-File: LICENSE
Classifier: Development Status :: 4 - Beta
Classifier: Intended Audience :: Science/Research
Classifier: License :: OSI Approved :: Apache Software License
Classifier: Operating System :: MacOS :: MacOS X
Classifier: Operating System :: POSIX :: Linux
Classifier: Programming Language :: Python :: 3
Requires-Python: >=3.10
Requires-Dist: equinox>=0.10.6
Requires-Dist: jaxtyping>=0.2.20
Requires-Dist: jmp>=0.0.4
Provides-Extra: dev
Requires-Dist: mkdocs-include-markdown-plugin; extra == 'dev'
Requires-Dist: mkdocs-literate-nav>=0.6.0; extra == 'dev'
Requires-Dist: mkdocs-macros-plugin>=0.7.0; extra == 'dev'
Requires-Dist: mkdocs-material>=7.3.3; extra == 'dev'
Requires-Dist: mkdocs>=1.4.3; extra == 'dev'
Requires-Dist: mkdocstrings-python>=1.1.2; extra == 'dev'
Requires-Dist: mkdocstrings>=0.22.0; extra == 'dev'
Requires-Dist: mypy>=0.910; extra == 'dev'
Requires-Dist: pygments; extra == 'dev'
Requires-Dist: pymdown-extensions; extra == 'dev'
Requires-Dist: pytest>=7.4.0; extra == 'dev'
